ai/__init__.py
ai/compliance_checker.py
ai/llm.py
ai/models.py
ai/risk_predictor.py
ai/urls.py
ai/views.py
ai/migrations/0001_initial.py
ai/migrations/0002_alter_aisuggestion_options_alter_chatmessage_options_and_more.py
ai/migrations/__init__.py
compliance/__init__.py
compliance/admin.py
compliance/apps.py
compliance/forms.py
compliance/models.py
compliance/urls.py
compliance/views.py
compliance/migrations/0001_initial.py
compliance/migrations/__init__.py
compliedge/__init__.py
compliedge/asgi.py
compliedge/settings.py
compliedge/urls.py
compliedge/views.py
compliedge/wsgi.py
compliedge-0.1.0.dist-info/licenses/LICENSE
dashboard/__init__.py
dashboard/admin.py
dashboard/apps.py
dashboard/models.py
dashboard/urls.py
dashboard/views.py
dashboard/migrations/0001_initial.py
dashboard/migrations/__init__.py
governance/__init__.py
governance/admin.py
governance/apps.py
governance/forms.py
governance/models.py
governance/urls.py
governance/views.py
governance/migrations/0001_initial.py
governance/migrations/__init__.py
governance/tests/__init__.py
governance/tests/test_models.py
notifications/__init__.py
notifications/email_utils.py
notifications/models.py
notifications/services.py
notifications/urls.py
notifications/views.py
notifications/management/__init__.py
notifications/management/commands/__init__.py
notifications/management/commands/send_smart_notifications.py
notifications/management/commands/test_email.py
notifications/migrations/0001_initial.py
notifications/migrations/__init__.py
pages/__init__.py
pages/urls.py
pages/views.py
permissions/__init__.py
permissions/company_decorators.py
permissions/company_mixins.py
permissions/decorators.py
permissions/middleware.py
permissions/mixins.py
permissions/utils.py
permissions/tests/__init__.py
permissions/tests/test_decorators.py
permissions/tests/test_mixins.py
permissions/tests/test_settings.py
permissions/tests/test_utils.py
permissions/tests/test_views.py
risk/__init__.py
risk/admin.py
risk/apps.py
risk/forms.py
risk/models.py
risk/urls.py
risk/views.py
compliedge-0.1.0.dist-info/METADATA
compliedge-0.1.0.dist-info/WHEEL
compliedge-0.1.0.dist-info/top_level.txt
compliedge-0.1.0.dist-info/RECORD
