Metadata-Version: 2.4
Name: CompliEdge
Version: 0.1.0
Summary: CompliEdge - Enterprise GRC Management System
Home-page: https://github.com/RajeshBasnet-dev/CompliEdge
Author: Rajesh Basnet
Author-email: basnetrajesh245@gmail.com
Classifier: Programming Language :: Python :: 3
Classifier: Framework :: Django
Classifier: License :: OSI Approved :: MIT License
Classifier: Operating System :: OS Independent
Requires-Python: >=3.8
License-File: LICENSE
Requires-Dist: Django<5.0.0,>=4.2.0
Requires-Dist: Pillow>=9.0.0
Requires-Dist: django-crispy-forms>=2.0.0
Requires-Dist: crispy-tailwind>=0.6.0
Requires-Dist: pyotp>=2.6.0
Requires-Dist: qrcode>=7.3.1
Requires-Dist: python-decouple>=3.6
Requires-Dist: requests>=2.31.0
Dynamic: author
Dynamic: author-email
Dynamic: classifier
Dynamic: description
Dynamic: description-content-type
Dynamic: home-page
Dynamic: license-file
Dynamic: requires-dist
Dynamic: requires-python
Dynamic: summary
